{"DZD": {"rate": 81.390876, "baseKey": "USD", "name": "Algerian Dinar", "key": "DZD"}, "NAD": {"rate": 9.966221, "baseKey": "USD", "name": "Namibian Dollar", "key": "NAD"}, "GHS": {"rate": 2.185408, "baseKey": "USD", "name": "Ghanaian Cedi", "key": "GHS"}, "EGP": {"rate": 6.891142, "baseKey": "USD", "name": "Egyptian Pound", "key": "EGP"}, "BGN": {"rate": 1.442226, "baseKey": "USD", "name": "Bulgarian Lev", "key": "BGN"}, "PAB": {"rate": 1.0, "baseKey": "USD", "name": "Panamanian Balboa", "key": "PAB"}, "PHP": {"rate": 43.113794, "baseKey": "USD", "name": "Philippine Peso", "key": "PHP"}, "BOB": {"rate": 6.909941, "baseKey": "USD", "name": "Bolivian Boliviano", "key": "BOB"}, "DKK": {"rate": 5.494464, "baseKey": "USD", "name": "Danish Krone", "key": "DKK"}, "BWP": {"rate": 8.501035, "baseKey": "USD", "name": "Botswanan Pula", "key": "BWP"}, "LBP": {"rate": 1510.741005, "baseKey": "USD", "name": "Lebanese Pound", "key": "LBP"}, "TZS": {"rate": 1609.86024, "baseKey": "USD", "name": "Tanzanian Shilling", "key": "TZS"}, "VND": {"rate": 21150.911425, "baseKey": "USD", "name": "Vietnamese Dong", "key": "VND"}, "AOA": {"rate": 97.572076, "baseKey": "USD", "name": "Angolan Kwanza", "key": "AOA"}, "KHR": {"rate": 4067.380167, "baseKey": "USD", "name": "Cambodian Riel", "key": "KHR"}, "QAR": {"rate": 3.641085, "baseKey": "USD", "name": "Qatari Rial", "key": "QAR"}, "KYD": {"rate": 0.821606, "baseKey": "USD", "name": "Cayman Islands Dollar", "key": "KYD"}, "LYD": {"rate": 1.244592, "baseKey": "USD", "name": "Libyan Dinar", "key": "LYD"}, "UAH": {"rate": 8.183744, "baseKey": "USD", "name": "Ukrainian Hryvnia", "key": "UAH"}, "JOD": {"rate": 0.70826, "baseKey": "USD", "name": "Jordanian Dinar", "key": "JOD"}, "AWG": {"rate": 1.790725, "baseKey": "USD", "name": "Aruban Florin", "key": "AWG"}, "SAR": {"rate": 3.750049, "baseKey": "USD", "name": "Saudi Riyal", "key": "SAR"}, "LTL": {"rate": 2.543452, "baseKey": "USD", "name": "Lithuanian Litas", "key": "LTL"}, "HKD": {"rate": 7.7543, "baseKey": "USD", "name": "Hong Kong Dollar", "key": "HKD"}, "CHF": {"rate": 0.903763, "baseKey": "USD", "name": "Swiss Franc", "key": "CHF"}, "GIP": {"rate": 0.621685, "baseKey": "USD", "name": "Gibraltar Pound", "key": "GIP"}, "BYR": {"rate": 9146.915, "baseKey": "USD", "name": "Belarusian Ruble", "key": "BYR"}, "XPF": {"rate": 87.88387, "baseKey": "USD", "name": "CFP Franc", "key": "XPF"}, "MRO": {"rate": 302.2274, "baseKey": "USD", "name": "Mauritanian Ouguiya", "key": "MRO"}, "HRK": {"rate": 5.615869, "baseKey": "USD", "name": "Croatian Kuna", "key": "HRK"}, "DJF": {"rate": 177.818999, "baseKey": "USD", "name": "Djiboutian Franc", "key": "DJF"}, "THB": {"rate": 31.359591, "baseKey": "USD", "name": "Thai Baht", "key": "THB"}, "XAF": {"rate": 483.556883, "baseKey": "USD", "name": "CFA Franc BEAC", "key": "XAF"}, "BND": {"rate": 1.248607, "baseKey": "USD", "name": "Brunei Dollar", "key": "BND"}, "ETB": {"rate": 18.93172, "baseKey": "USD", "name": "Ethiopian Birr", "key": "ETB"}, "UYU": {"rate": 21.52226, "baseKey": "USD", "name": "Uruguayan Peso", "key": "UYU"}, "NIO": {"rate": 24.852728, "baseKey": "USD", "name": "Nicaraguan C\u00f3rdoba", "key": "NIO"}, "LAK": {"rate": 7857.628333, "baseKey": "USD", "name": "Laotian Kip", "key": "LAK"}, "SYP": {"rate": 137.326874, "baseKey": "USD", "name": "Syrian Pound", "key": "SYP"}, "MAD": {"rate": 8.26171, "baseKey": "USD", "name": "Moroccan Dirham", "key": "MAD"}, "MZN": {"rate": 29.638025, "baseKey": "USD", "name": "Mozambican Metical", "key": "MZN"}, "YER": {"rate": 215.040602, "baseKey": "USD", "name": "Yemeni Rial", "key": "YER"}, "ZAR": {"rate": 9.980763, "baseKey": "USD", "name": "South African Rand", "key": "ZAR"}, "NPR": {"rate": 98.922125, "baseKey": "USD", "name": "Nepalese Rupee", "key": "NPR"}, "ZWL": {"rate": 322.355006, "baseKey": "USD", "name": "Zimbabwean Dollar", "key": "ZWL"}, "NGN": {"rate": 160.196881, "baseKey": "USD", "name": "Nigerian Naira", "key": "NGN"}, "CRC": {"rate": 500.727643, "baseKey": "USD", "name": "Costa Rican Col\u00f3n", "key": "CRC"}, "AED": {"rate": 3.672856, "baseKey": "USD", "name": "United Arab Emirates Dirham", "key": "AED"}, "EEK": {"rate": 11.712857, "baseKey": "USD", "name": "Estonian Kroon", "key": "EEK"}, "MWK": {"rate": 368.6734, "baseKey": "USD", "name": "Malawian Kwacha", "key": "MWK"}, "TTD": {"rate": 6.412627, "baseKey": "USD", "name": "Trinidad and Tobago Dollar", "key": "TTD"}, "LKR": {"rate": 131.190423, "baseKey": "USD", "name": "Sri Lankan Rupee", "key": "LKR"}, "PKR": {"rate": 106.034974, "baseKey": "USD", "name": "Pakistani Rupee", "key": "PKR"}, "HUF": {"rate": 217.729456, "baseKey": "USD", "name": "Hungarian Forint", "key": "HUF"}, "BMD": {"rate": 1.0, "baseKey": "USD", "name": "Bermudan Dollar", "key": "BMD"}, "LSL": {"rate": 9.964281, "baseKey": "USD", "name": "Lesotho Loti", "key": "LSL"}, "MNT": {"rate": 1657.333333, "baseKey": "USD", "name": "Mongolian Tugrik", "key": "MNT"}, "AMD": {"rate": 409.541, "baseKey": "USD", "name": "Armenian Dram", "key": "AMD"}, "UGX": {"rate": 2545.137315, "baseKey": "USD", "name": "Ugandan Shilling", "key": "UGX"}, "XDR": {"rate": 0.650438, "baseKey": "USD", "name": "Special Drawing Rights", "key": "XDR"}, "JMD": {"rate": 103.563232, "baseKey": "USD", "name": "Jamaican Dollar", "key": "JMD"}, "GEL": {"rate": 1.66275, "baseKey": "USD", "name": "Georgian Lari", "key": "GEL"}, "SHP": {"rate": 0.621685, "baseKey": "USD", "name": "Saint Helena Pound", "key": "SHP"}, "AFN": {"rate": 56.464575, "baseKey": "USD", "name": "Afghan Afghani", "key": "AFN"}, "MMK": {"rate": 968.90112, "baseKey": "USD", "name": "Myanma Kyat", "key": "MMK"}, "KPW": {"rate": 900.0, "baseKey": "USD", "name": "North Korean Won", "key": "KPW"}, "TRY": {"rate": 1.990479, "baseKey": "USD", "name": "Turkish Lira", "key": "TRY"}, "BDT": {"rate": 77.66488, "baseKey": "USD", "name": "Bangladeshi Taka", "key": "BDT"}, "CNY": {"rate": 6.123696, "baseKey": "USD", "name": "Chinese Yuan", "key": "CNY"}, "HTG": {"rate": 43.13914, "baseKey": "USD", "name": "Haitian Gourde", "key": "HTG"}, "SLL": {"rate": 4318.336333, "baseKey": "USD", "name": "Sierra Leonean Leone", "key": "SLL"}, "MGA": {"rate": 2237.596667, "baseKey": "USD", "name": "Malagasy Ariary", "key": "MGA"}, "ANG": {"rate": 1.78896, "baseKey": "USD", "name": "Netherlands Antillean Guilder", "key": "ANG"}, "LRD": {"rate": 80.383332, "baseKey": "USD", "name": "Liberian Dollar", "key": "LRD"}, "RWF": {"rate": 671.79062, "baseKey": "USD", "name": "Rwandan Franc", "key": "RWF"}, "NOK": {"rate": 5.973102, "baseKey": "USD", "name": "Norwegian Krone", "key": "NOK"}, "MOP": {"rate": 7.986831, "baseKey": "USD", "name": "Macanese Pataca", "key": "MOP"}, "INR": {"rate": 61.824554, "baseKey": "USD", "name": "Indian Rupee", "key": "INR"}, "MXN": {"rate": 13.171431, "baseKey": "USD", "name": "Mexican Peso", "key": "MXN"}, "CZK": {"rate": 18.794765, "baseKey": "USD", "name": "Czech Republic Koruna", "key": "CZK"}, "TJS": {"rate": 4.7683, "baseKey": "USD", "name": "Tajikistani Somoni", "key": "TJS"}, "BTC": {"rate": 0.00763157, "baseKey": "USD", "name": "Bitcoin", "key": "BTC"}, "BTN": {"rate": 61.787676, "baseKey": "USD", "name": "Bhutanese Ngultrum", "key": "BTN"}, "COP": {"rate": 1887.604793, "baseKey": "USD", "name": "Colombian Peso", "key": "COP"}, "MYR": {"rate": 3.193253, "baseKey": "USD", "name": "Malaysian Ringgit", "key": "MYR"}, "TMT": {"rate": 2.8501, "baseKey": "USD", "name": "Turkmenistani Manat", "key": "TMT"}, "MUR": {"rate": 30.377961, "baseKey": "USD", "name": "Mauritian Rupee", "key": "MUR"}, "IDR": {"rate": 11436.013225, "baseKey": "USD", "name": "Indonesian Rupiah", "key": "IDR"}, "HNL": {"rate": 20.451608, "baseKey": "USD", "name": "Honduran Lempira", "key": "HNL"}, "FJD": {"rate": 1.850159, "baseKey": "USD", "name": "Fijian Dollar", "key": "FJD"}, "ISK": {"rate": 121.197999, "baseKey": "USD", "name": "Icelandic Kr\u00f3na", "key": "ISK"}, "PEN": {"rate": 2.780441, "baseKey": "USD", "name": "Peruvian Nuevo Sol", "key": "PEN"}, "BZD": {"rate": 1.987329, "baseKey": "USD", "name": "Belize Dollar", "key": "BZD"}, "ILS": {"rate": 3.5558, "baseKey": "USD", "name": "Israeli New Sheqel", "key": "ILS"}, "DOP": {"rate": 42.409768, "baseKey": "USD", "name": "Dominican Peso", "key": "DOP"}, "AZN": {"rate": 0.7842, "baseKey": "USD", "name": "Azerbaijani Manat", "key": "AZN"}, "MDL": {"rate": 13.103427, "baseKey": "USD", "name": "Moldovan Leu", "key": "MDL"}, "BSD": {"rate": 1.0, "baseKey": "USD", "name": "Bahamian Dollar", "key": "BSD"}, "SEK": {"rate": 6.427875, "baseKey": "USD", "name": "Swedish Krona", "key": "SEK"}, "ZMK": {"rate": 5230.441665, "baseKey": "USD", "name": "Zambian Kwacha (pre-2013)", "key": "ZMK"}, "JEP": {"rate": 0.621685, "baseKey": "USD", "name": "Jersey Pound", "key": "JEP"}, "AUD": {"rate": 1.059758, "baseKey": "USD", "name": "Australian Dollar", "key": "AUD"}, "SRD": {"rate": 3.283333, "baseKey": "USD", "name": "Surinamese Dollar", "key": "SRD"}, "CUP": {"rate": 22.687419, "baseKey": "USD", "name": "Cuban Peso", "key": "CUP"}, "CLF": {"rate": 0.02165, "baseKey": "USD", "name": "Chilean Unit of Account (UF)", "key": "CLF"}, "BBD": {"rate": 2.0, "baseKey": "USD", "name": "Barbadian Dollar", "key": "BBD"}, "KMF": {"rate": 362.483768, "baseKey": "USD", "name": "Comorian Franc", "key": "KMF"}, "KRW": {"rate": 1072.982852, "baseKey": "USD", "name": "South Korean Won", "key": "KRW"}, "GMD": {"rate": 32.94789, "baseKey": "USD", "name": "Gambian Dalasi", "key": "GMD"}, "VEF": {"rate": 6.292861, "baseKey": "USD", "name": "Venezuelan Bol\u00edvar Fuerte", "key": "VEF"}, "GTQ": {"rate": 7.971265, "baseKey": "USD", "name": "Guatemalan Quetzal", "key": "GTQ"}, "CLP": {"rate": 499.814022, "baseKey": "USD", "name": "Chilean Peso", "key": "CLP"}, "ZMW": {"rate": 5.285537, "baseKey": "USD", "name": "Zambian Kwacha", "key": "ZMW"}, "EUR": {"rate": 0.736507, "baseKey": "USD", "name": "Euro", "key": "EUR"}, "ALL": {"rate": 104.2434, "baseKey": "USD", "name": "Albanian Lek", "key": "ALL"}, "XCD": {"rate": 2.70154, "baseKey": "USD", "name": "East Caribbean Dollar", "key": "XCD"}, "KZT": {"rate": 154.291728, "baseKey": "USD", "name": "Kazakhstani Tenge", "key": "KZT"}, "RUB": {"rate": 32.35013, "baseKey": "USD", "name": "Russian Ruble", "key": "RUB"}, "XAG": {"rate": 0.04412962, "baseKey": "USD", "name": "Silver (troy ounce)", "key": "XAG"}, "CDF": {"rate": 925.099167, "baseKey": "USD", "name": "Congolese Franc", "key": "CDF"}, "RON": {"rate": 3.267457, "baseKey": "USD", "name": "Romanian Leu", "key": "RON"}, "OMR": {"rate": 0.384973, "baseKey": "USD", "name": "Omani Rial", "key": "OMR"}, "BRL": {"rate": 2.208471, "baseKey": "USD", "name": "Brazilian Real", "key": "BRL"}, "SBD": {"rate": 7.108715, "baseKey": "USD", "name": "Solomon Islands Dollar", "key": "SBD"}, "PLN": {"rate": 3.090898, "baseKey": "USD", "name": "Polish Zloty", "key": "PLN"}, "PYG": {"rate": 4457.77111, "baseKey": "USD", "name": "Paraguayan Guarani", "key": "PYG"}, "KES": {"rate": 85.017615, "baseKey": "USD", "name": "Kenyan Shilling", "key": "KES"}, "MKD": {"rate": 45.292963, "baseKey": "USD", "name": "Macedonian Denar", "key": "MKD"}, "GBP": {"rate": 0.621685, "baseKey": "USD", "name": "British Pound Sterling", "key": "GBP"}, "TWD": {"rate": 29.371504, "baseKey": "USD", "name": "New Taiwan Dollar", "key": "TWD"}, "TOP": {"rate": 1.794633, "baseKey": "USD", "name": "Tongan Pa\u02bbanga", "key": "TOP"}, "MVR": {"rate": 15.41866, "baseKey": "USD", "name": "Maldivian Rufiyaa", "key": "MVR"}, "VUV": {"rate": 95.089999, "baseKey": "USD", "name": "Vanuatu Vatu", "key": "VUV"}, "GNF": {"rate": 6902.0503, "baseKey": "USD", "name": "Guinean Franc", "key": "GNF"}, "WST": {"rate": 2.313804, "baseKey": "USD", "name": "Samoan Tala", "key": "WST"}, "IQD": {"rate": 1165.193383, "baseKey": "USD", "name": "Iraqi Dinar", "key": "IQD"}, "BAM": {"rate": 1.441339, "baseKey": "USD", "name": "Bosnia-Herzegovina Convertible Mark", "key": "BAM"}, "SCR": {"rate": 12.063141, "baseKey": "USD", "name": "Seychellois Rupee", "key": "SCR"}, "CAD": {"rate": 1.034619, "baseKey": "USD", "name": "Canadian Dollar", "key": "CAD"}, "CVE": {"rate": 80.642, "baseKey": "USD", "name": "Cape Verdean Escudo", "key": "CVE"}, "KWD": {"rate": 0.282848, "baseKey": "USD", "name": "Kuwaiti Dinar", "key": "KWD"}, "BIF": {"rate": 1541.4384, "baseKey": "USD", "name": "Burundian Franc", "key": "BIF"}, "PGK": {"rate": 2.513696, "baseKey": "USD", "name": "Papua New Guinean Kina", "key": "PGK"}, "SOS": {"rate": 1247.113367, "baseKey": "USD", "name": "Somali Shilling", "key": "SOS"}, "SGD": {"rate": 1.249143, "baseKey": "USD", "name": "Singapore Dollar", "key": "SGD"}, "UZS": {"rate": 2157.564434, "baseKey": "USD", "name": "Uzbekistan Som", "key": "UZS"}, "STD": {"rate": 18058.267333, "baseKey": "USD", "name": "S\u00e3o Tom\u00e9 and Pr\u00edncipe Dobra", "key": "STD"}, "IRR": {"rate": 24803.7177, "baseKey": "USD", "name": "Iranian Rial", "key": "IRR"}, "SVC": {"rate": 8.747766, "baseKey": "USD", "name": "Salvadoran Col\u00f3n", "key": "SVC"}, "XOF": {"rate": 483.73902, "baseKey": "USD", "name": "CFA Franc BCEAO", "key": "XOF"}, "TND": {"rate": 1.64579, "baseKey": "USD", "name": "Tunisian Dinar", "key": "TND"}, "GYD": {"rate": 202.104999, "baseKey": "USD", "name": "Guyanaese Dollar", "key": "GYD"}, "MTL": {"rate": 0.683602, "baseKey": "USD", "name": "Maltese Lira", "key": "MTL"}, "NZD": {"rate": 1.203999, "baseKey": "USD", "name": "New Zealand Dollar", "key": "NZD"}, "FKP": {"rate": 0.621685, "baseKey": "USD", "name": "Falkland Islands Pound", "key": "FKP"}, "LVL": {"rate": 0.517545, "baseKey": "USD", "name": "Latvian Lats", "key": "LVL"}, "USD": {"rate": 1.0, "baseKey": "USD", "name": "United States Dollar", "key": "USD"}, "KGS": {"rate": 48.899775, "baseKey": "USD", "name": "Kyrgystani Som", "key": "KGS"}, "ARS": {"rate": 5.820467, "baseKey": "USD", "name": "Argentine Peso", "key": "ARS"}, "SZL": {"rate": 9.966291, "baseKey": "USD", "name": "Swazi Lilangeni", "key": "SZL"}, "RSD": {"rate": 84.190931, "baseKey": "USD", "name": "Serbian Dinar", "key": "RSD"}, "BHD": {"rate": 0.376944, "baseKey": "USD", "name": "Bahraini Dinar", "key": "BHD"}, "JPY": {"rate": 96.954451, "baseKey": "USD", "name": "Japanese Yen", "key": "JPY"}, "SDG": {"rate": 4.409285, "baseKey": "USD", "name": "Sudanese Pound", "key": "SDG"}, "XAU": {"rate": 0.00075775, "baseKey": "USD", "name": "Gold (troy ounce)", "key": "XAU"},"timestamp": 1381276922.329544}